arc_stack-0.1.2.dist-info/licenses/LICENSE
stack/cli_utils.py
stack/dataloader.py
stack/finetuning_dataloader.py
stack/model.py
stack/model_finetune.py
stack/model_loading.py
stack/cli/__init__.py
stack/cli/embedding.py
stack/cli/generation.py
stack/cli/launch_finetuning.py
stack/cli/launch_training.py
stack/data/__init__.py
stack/data/datasets.py
stack/data/gene_processing.py
stack/data/h5_manager.py
stack/data/hvg.py
stack/data/finetuning/__init__.py
stack/data/finetuning/datasets.py
stack/data/training/__init__.py
stack/data/training/datasets.py
stack/finetune/__init__.py
stack/finetune/datamodule.py
stack/finetune/datasets.py
stack/finetune/lightning.py
stack/finetune/utils.py
stack/models/__init__.py
stack/models/utils.py
stack/models/core/__init__.py
stack/models/core/base.py
stack/models/core/inference.py
stack/models/core/losses.py
stack/models/finetune/__init__.py
stack/models/finetune/mixins.py
stack/models/finetune/model.py
stack/modules/__init__.py
stack/modules/attention.py
stack/modules/regularizers.py
stack/training/__init__.py
stack/training/datamodule.py
stack/training/lightning.py
stack/training/utils.py
arc_stack-0.1.2.dist-info/METADATA
arc_stack-0.1.2.dist-info/WHEEL
arc_stack-0.1.2.dist-info/entry_points.txt
arc_stack-0.1.2.dist-info/top_level.txt
arc_stack-0.1.2.dist-info/RECORD
