Metadata-Version: 2.4
Name: arc-stack
Version: 0.1.2
Summary: Stack is a single-cell foundation model that enables in-context learning at inference time.
Author-email: Mingze Dong <mingze.dong@arcinstitute.org>, Yusuf Roohani <yusuf.roohani@arcinstitute.org>
License: Attribution-NonCommercial-ShareAlike 4.0 International
Project-URL: Homepage, https://github.com/ArcInstitute/stack
Project-URL: Source, https://github.com/ArcInstitute/stack
Requires-Python: >=3.9
License-File: LICENSE
Requires-Dist: anndata>=0.9
Requires-Dist: h5py>=3.8
Requires-Dist: geomloss>=0.2.6
Requires-Dist: numpy>=1.22
Requires-Dist: pandas>=1.5
Requires-Dist: psutil>=5.9
Requires-Dist: pytorch-lightning>=2.1
Requires-Dist: PyYAML>=6.0
Requires-Dist: scipy>=1.8
Requires-Dist: scvi-tools>=1.0
Requires-Dist: torch>=2.0
Requires-Dist: wandb>=0.15
Dynamic: license-file
